Workbook

Sheet Read Me
B2: Cash Waqf / Islamic Social Finance Impact Model
B3: A revolving Qard-e-Hasan (interest-free loan) fund model, in the tradition of Pakistan's Akhuwat Foundation
B5: PURPOSE
B6: Millions of low-income Pakistani households cannot get an affordable loan from either a conventional bank (no
B7: collateral, no credit history) or a typical microfinance institution (interest rates on small loans are often
B8: very high once fees and mark-ups are included) - and routinely turn to informal moneylenders charging 5-10% PER
B9: MONTH, an effective annual cost that can trap a household in debt rather than lifting it out of poverty.
B10: Pakistan's own Akhuwat Foundation pioneered a different model at national scale: QARD-E-HASAN, an interest-free
B11: loan funded by a revolving pool of donations (a form of cash waqf/philanthropic endowment), often disbursed
B12: through mosques and repaid on trust and community/social accountability rather than collateral - and Akhuwat
B13: has reported extraordinarily low default rates (commonly cited around 1-2%) as a result. This project builds a
B14: financial model of exactly this mechanism: a revolving Qard-e-Hasan fund, its sustainability, and the welfare it
... B36: here as a realistic illustrative parameter, not a reproduction of their reported figures.

Sheet Assumptions
B2: Model Assumptions - Revolving Qard-e-Hasan Fund
B4: Assumption | C4: Value
B5: Initial Waqf/Donation Corpus (PKR) | C5: 50000000
B6: Annual New Donations Inflow (PKR) | C6: 15000000
B7: Average Loan Size per Borrower (PKR) | C7: 60000
B8: Loan Write-off / Default Rate (annual) | C8: 0.02
B9: Service Fee Rate (one-time, cost-recovery only - not interest) | C9: 0.05
B10: Operating Cost per Borrower per Year (PKR) | C10: 3000
B11: Estimated Household Income Uplift per Loan (PKR/year) | C11: 18000
B12: Avg Household Size (persons benefiting per loan) | C12: 5.8
B13: Typical Informal Moneylender Annual Cost (illustrative) | C13: 0.6

Sheet Revolving Fund Model
B2: Revolving Qard-e-Hasan Fund - 10-Year Model
B4: Line Item | C4: Year 1 | D4: Year 2 | E4: Year 3 | F4: Year 4 | G4: Year 5 | H4: Year 6 | I4: Year 7 | J4: Year 8 | K4: Year 9 | L4: Year 10
B5: Beginning Corpus | C5: =Assumptions!$C$5 | D5: =C13 | E5: =D13 | F5: =E13 | G5: =F13 | H5: =G13 | I5: =H13 | J5: =I13 | K5: =J13 | L5: =K13
B6: New Donations Inflow | C6: =Assumptions!$C$6 | D6: =Assumptions!$C$6 | E6: =Assumptions!$C$6 | F6: =Assumptions!$C$6 | G6: =Assumptions!$C$6 | H6: =Assumptions!$C$6 | I6: =Assumptions!$C$6 | J6: =Assumptions!$C$6 | ... L6: =Assumptions!$C$6
B7: Available to Lend | C7: =C5+C6 | D7: =D5+D6 | E7: =E5+E6 | F7: =F5+F6 | G7: =G5+G6 | H7: =H5+H6 | I7: =I5+I6 | J7: =J5+J6 | ... L7: =L5+L6
B8: Loans Disbursed (fund fully deployed - demand exceeds supply) | C8: =C7 | D8: =D7 | E8: =E7 | F8: =F7 | G8: =G7 | H8: =H7 | I8: =I7 | J8: =J7 | ... L8: =L7
B9: Borrowers Served | C9: =C8/Assumptions!$C$7 | D9: =D8/Assumptions!$C$7 | E9: =E8/Assumptions!$C$7 | F9: =F8/Assumptions!$C$7 | G9: =G8/Assumptions!$C$7 | H9: =H8/Assumptions!$C$7 | I9: =I8/Assumptions!$C$7 | J9: =J8/Assumptions!$C$7 | ... L9: =L8/Assumptions!$C$7
B10: Write-offs (Defaults) | C10: =C8*Assumptions!$C$8 | D10: =D8*Assumptions!$C$8 | E10: =E8*Assumptions!$C$8 | F10: =F8*Assumptions!$C$8 | G10: =G8*Assumptions!$C$8 | H10: =H8*Assumptions!$C$8 | I10: =I8*Assumptions!$C$8 | J10: =J8*Assumptions!$C$8 | ... L10: =L8*Assumptions!$C$8
B11: Service Fees Collected | C11: =C8*Assumptions!$C$9 | D11: =D8*Assumptions!$C$9 | E11: =E8*Assumptions!$C$9 | F11: =F8*Assumptions!$C$9 | G11: =G8*Assumptions!$C$9 | H11: =H8*Assumptions!$C$9 | I11: =I8*Assumptions!$C$9 | J11: =J8*Assumptions!$C$9 | ... L11: =L8*Assumptions!$C$9
B12: Operating Costs | C12: =C9*Assumptions!$C$10 | D12: =D9*Assumptions!$C$10 | E12: =E9*Assumptions!$C$10 | F12: =F9*Assumptions!$C$10 | G12: =G9*Assumptions!$C$10 | H12: =H9*Assumptions!$C$10 | I12: =I9*Assumptions!$C$10 | J12: =J9*Assumptions!$C$10 | ... L12: =L9*Assumptions!$C$10
B13: Ending Corpus (Principal Recovered + Fees - Opex) | C13: =(C8-C10)+C11-C12 | D13: =(D8-D10)+D11-D12 | E13: =(E8-E10)+E11-E12 | F13: =(F8-F10)+F11-F12 | G13: =(G8-G10)+G11-G12 | H13: =(H8-H10)+H11-H12 | I13: =(I8-I10)+I11-I12 | J13: =(J8-J10)+J11-J12 | ... L13: =(L8-L10)+L11-L12
B15: CUMULATIVE Borrowers Served (since inception) | C15: =C9 | D15: =C15+D9 | E15: =D15+E9 | F15: =E15+F9 | G15: =F15+G9 | H15: =G15+H9 | I15: =H15+I9 | J15: =I15+J9 | K15: =J15+K9 | L15: =K15+L9
B16: Self-Sustainability Ratio ((Fees+Repaid Principal) / Available to Lend) | C16: =((C8-C10)+C11)/C7 | D16: =((D8-D10)+D11)/D7 | E16: =((E8-E10)+E11)/E7 | F16: =((F8-F10)+F11)/F7 | G16: =((G8-G10)+G11)/G7 | H16: =((H8-H10)+H11)/H7 | I16: =((I8-I10)+I11)/I7 | J16: =((J8-J10)+J11)/J7 | ... L16: =((L8-L10)+L11)/L7

Sheet Social Impact & Interest Saved
B2: Social Impact & Interest-Avoided Analysis
B3: Compares the Qard-e-Hasan service fee against a typical informal moneylender's cost for the same loan.
B5: Line Item | C5: Year 1 | D5: Year 2 | E5: Year 3 | F5: Year 4 | G5: Year 5 | H5: Year 6 | I5: Year 7 | J5: Year 8 | K5: Year 9 | L5: Year 10
B6: Estimated Total Household Income Uplift (Borrowers x Uplift/Loan) | C6: ='Revolving Fund Model'!C9*Assumptions!$C$11 | D6: ='Revolving Fund Model'!D9*Assumptions!$C$11 | E6: ='Revolving Fund Model'!E9*Assumptions!$C$11 | F6: ='Revolving Fund Model'!F9*Assumptions!$C$11 | G6: ='Revolving Fund Model'!G9*Assumptions!$C$11 | H6: ='Revolving Fund Model'!H9*Assumptions!$C$11 | I6: ='Revolving Fund Model'!I9*Assumptions!$C$11 | J6: ='Revolving Fund Model'!J9*Assumptions!$C$11 | ... L6: ='Revolving Fund Model'!L9*Assumptions!$C$11
B7: Estimated People Reached (Borrowers x Household Size) | C7: ='Revolving Fund Model'!C9*Assumptions!$C$12 | D7: ='Revolving Fund Model'!D9*Assumptions!$C$12 | E7: ='Revolving Fund Model'!E9*Assumptions!$C$12 | F7: ='Revolving Fund Model'!F9*Assumptions!$C$12 | G7: ='Revolving Fund Model'!G9*Assumptions!$C$12 | H7: ='Revolving Fund Model'!H9*Assumptions!$C$12 | I7: ='Revolving Fund Model'!I9*Assumptions!$C$12 | J7: ='Revolving Fund Model'!J9*Assumptions!$C$12 | ... L7: ='Revolving Fund Model'!L9*Assumptions!$C$12
B8: Cost if Borrowed from Informal Moneylender Instead (Disbursed x Informal Rate) | C8: ='Revolving Fund Model'!C8*Assumptions!$C$13 | D8: ='Revolving Fund Model'!D8*Assumptions!$C$13 | E8: ='Revolving Fund Model'!E8*Assumptions!$C$13 | F8: ='Revolving Fund Model'!F8*Assumptions!$C$13 | G8: ='Revolving Fund Model'!G8*Assumptions!$C$13 | H8: ='Revolving Fund Model'!H8*Assumptions!$C$13 | I8: ='Revolving Fund Model'!I8*Assumptions!$C$13 | J8: ='Revolving Fund Model'!J8*Assumptions!$C$13 | ... L8: ='Revolving Fund Model'!L8*Assumptions!$C$13
B9: Actual Cost Paid (Service Fee Only) | C9: ='Revolving Fund Model'!C11 | D9: ='Revolving Fund Model'!D11 | E9: ='Revolving Fund Model'!E11 | F9: ='Revolving Fund Model'!F11 | G9: ='Revolving Fund Model'!G11 | H9: ='Revolving Fund Model'!H11 | I9: ='Revolving Fund Model'!I11 | J9: ='Revolving Fund Model'!J11 | ... L9: ='Revolving Fund Model'!L11
B10: INTEREST/COST BURDEN AVOIDED (Informal Cost - Actual Fee) | C10: =C8-C9 | D10: =D8-D9 | E10: =E8-E9 | F10: =F8-F9 | G10: =G8-G9 | H10: =H8-H9 | I10: =I8-I9 | J10: =J8-J9 | ... L10: =L8-L9
B12: CUMULATIVE Interest/Cost Burden Avoided (since inception) | C12: =C10 | D12: =C12+D10 | E12: =D12+E10 | F12: =E12+F10 | G12: =F12+G10 | H12: =G12+H10 | I12: =H12+I10 | J12: =I12+J10 | K12: =J12+K10 | L12: =K12+L10
B13: CUMULATIVE Estimated Household Income Uplift (since inception) | C13: =C6 | D13: =C13+D6 | E13: =D13+E6 | F13: =E13+F6 | G13: =F13+G6 | H13: =G13+H6 | I13: =H13+I6 | J13: =I13+J6 | K13: =J13+K6 | L13: =K13+L6
B15: CUMULATIVE Donations Received (Initial Corpus + Annual Inflows) | C15: =Assumptions!$C$5+'Revolving Fund Model'!C6 | D15: =C15+'Revolving Fund Model'!D6 | E15: =D15+'Revolving Fund Model'!E6 | F15: =E15+'Revolving Fund Model'!F6 | G15: =F15+'Revolving Fund Model'!G6 | H15: =G15+'Revolving Fund Model'!H6 | I15: =H15+'Revolving Fund Model'!I6 | J15: =I15+'Revolving Fund Model'!J6 | K15: =J15+'Revolving Fund Model'!K6 | L15: =K15+'Revolving Fund Model'!L6
B16: Social Value Multiplier (Cumulative Interest Avoided + Income Uplift, per PKR Donated) | C16: =(C12+C13)/C15 | D16: =(D12+D13)/D15 | E16: =(E12+E13)/E15 | F16: =(F12+F13)/F15 | G16: =(G12+G13)/G15 | H16: =(H12+H13)/H15 | I16: =(I12+I13)/I15 | J16: =(J12+J13)/J15 | ... L16: =(L12+L13)/L15

Sheet Dashboard
B2: Impact Dashboard

Sheet Insights
B2: Key Findings & Recommendations
B4: 1. THE REVOLVING STRUCTURE IS SELF-REINFORCING: the Self-Sustainability Ratio stays above 100% every year in this
B5: model (service fees plus recovered principal exceed what was lent out even after write-offs), meaning the fund
B6: grows on its own operating economics BEFORE counting new donations - donations accelerate growth and reach,
B7: but the fund is not dependent on them to survive, which is the central design insight behind why Akhuwat-style
B8: Qard-e-Hasan funds can scale nationally rather than staying a small, donor-dependent charity.
B9: 2. A LOW DEFAULT RATE IS THE MODEL'S LOAD-BEARING ASSUMPTION: because there is no interest income to absorb
B10: losses, sustainability depends much more heavily on keeping write-offs low than a conventional lender's model
B11: does - which is exactly why Akhuwat's mosque-based, social-collateral disbursement model (peer/community
B12: accountability rather than collateral) is not an incidental cultural detail but the financial engine that makes
B13: interest-free lending viable at scale.
B14: 3. THE INTEREST-AVOIDED METRIC IS THE MOST DISTINCTIVE OUTPUT OF THIS MODEL: borrowers pay a one-time ~5% service
... B29: profit-maximising one.
