Workbook

Sheet Read Me
B2: Household Budget & Inflation-Adjusted Savings Planner
B3: A budgeting and long-term savings tool built for Pakistan's high-inflation environment
B5: PURPOSE
B6: Pakistan has experienced some of the highest and most volatile inflation of any major economy in the last five
B7: years: Pakistan Bureau of Statistics (PBS) CPI data shows average annual inflation rising from roughly 8-12%
B8: (FY2019-FY2022) to a peak of around 29% in FY2023 (with individual months touching ~38% YoY) before cooling
B9: sharply as State Bank of Pakistan (SBP) tightened policy. For an ordinary household, this means a budget that
B10: worked last year can be badly wrong this year, and 'saving for retirement' or a child's education without
B11: explicitly planning for inflation quietly erodes real purchasing power - a household saving in a low-interest
B12: savings account can easily be losing money in real terms even while their account balance grows.
B14: HOW IT WORKS
B15: 1. 'Monthly Budget' - a standard household budget (income vs. 9 expense categories, budgeted vs. actual), with
... B31: illustrative middle-income Pakistani household (PKR), not real financial data.

Sheet Monthly Budget
B2: Monthly Household Budget
B3: PKR - edit 'Budgeted' and 'Actual' columns (yellow).
B5: Category | C5: Budgeted (PKR) | D5: Actual (PKR) | E5: Variance | F5: Variance % | H5: Abs Actual
B6: Income (net salary + other) | C6: 250000 | D6: 258000 | E6: =D6-C6 | F6: =IF(C6=0,0,(D6-C6)/ABS(C6))
B7: Rent / Housing | C7: -60000 | D7: -60000 | E7: =D7-C7 | F7: =IF(C7=0,0,(D7-C7)/ABS(C7)) | H7: =ABS(D7)
B8: Utilities (electricity, gas, water, internet) | C8: -35000 | D8: -42000 | E8: =D8-C8 | F8: =IF(C8=0,0,(D8-C8)/ABS(C8)) | H8: =ABS(D8)
B9: Groceries & Food | C9: -55000 | D9: -58000 | E9: =D9-C9 | F9: =IF(C9=0,0,(D9-C9)/ABS(C9)) | H9: =ABS(D9)
B10: Transport & Fuel | C10: -25000 | D10: -27000 | E10: =D10-C10 | F10: =IF(C10=0,0,(D10-C10)/ABS(C10)) | H10: =ABS(D10)
B11: Education (school/tuition fees) | C11: -30000 | D11: -30000 | E11: =D11-C11 | F11: =IF(C11=0,0,(D11-C11)/ABS(C11)) | H11: =ABS(D11)
B12: Healthcare & Insurance | C12: -12000 | D12: -9000 | E12: =D12-C12 | F12: =IF(C12=0,0,(D12-C12)/ABS(C12)) | H12: =ABS(D12)
B13: Debt / Loan Payments | C13: -15000 | D13: -15000 | E13: =D13-C13 | F13: =IF(C13=0,0,(D13-C13)/ABS(C13)) | H13: =ABS(D13)
B14: Discretionary (eating out, entertainment) | C14: -18000 | D14: -24000 | E14: =D14-C14 | F14: =IF(C14=0,0,(D14-C14)/ABS(C14)) | H14: =ABS(D14)
B15: Savings & Investments | C15: -30000 | D15: =D6+SUM(D7:D14) | E15: =D15-C15 | F15: =IF(C15=0,0,(D15-C15)/ABS(C15))
B17: Net Cash Flow (Budgeted) | C17: =SUM(C6:C15)
B18: Net Cash Flow (Actual) | D18: =D15

Sheet Inflation History (PBS)
B2: Pakistan Annual CPI Inflation - Historical Reference
B3: Representative approximation of PBS/SBP-reported average annual CPI inflation (%), FY basis.
B5: Fiscal Year | C5: Avg Annual CPI Inflation %
B6: FY2015 | C6: 0.045
B7: FY2016 | C7: 0.029
B8: FY2017 | C8: 0.042
B9: FY2018 | C9: 0.039
B10: FY2019 | C10: 0.073
B11: FY2020 | C11: 0.107
B12: FY2021 | C12: 0.089
B13: FY2022 | C13: 0.122
B14: FY2023 | C14: 0.292
B15: FY2024 | C15: 0.234
B16: FY2025 (est.) | C16: 0.065
B18: 10-Year Average Inflation | C18: =AVERAGE(C6:C16)

Sheet Inflation Planner
B2: Inflation-Adjusted Expense Projection
B4: Today's Total Annual Expenses (PKR): | D4: 2760000
B5: Assumed Average Annual Inflation Rate: | D5: ='Inflation History (PBS)'!C18
B6: Assumed Nominal Return on Savings/Investments: | D6: 0.13
B7: Real (Inflation-Adjusted) Return Needed Just to Preserve Value: | D7: =(1+D6)/(1+D5)-1
B9: Years from Now | C9: Projected Annual Expenses (Nominal PKR) | D9: Same Basket, Today's Purchasing Power (Real, constant PKR)
B10: 0 | C10: =$D$4*(1+$D$5)^B10 | D10: =$D$4
B11: 1 | C11: =$D$4*(1+$D$5)^B11 | D11: =$D$4
B12: 3 | C12: =$D$4*(1+$D$5)^B12 | D12: =$D$4
B13: 5 | C13: =$D$4*(1+$D$5)^B13 | D13: =$D$4
B14: 10 | C14: =$D$4*(1+$D$5)^B14 | D14: =$D$4
B15: 15 | C15: =$D$4*(1+$D$5)^B15 | D15: =$D$4
B16: 20 | C16: =$D$4*(1+$D$5)^B16 | D16: =$D$4
B18: Reading this table: the nominal PKR figure you'll need just to buy the SAME basket of goods grows every year at the inflation rate; the real (constant-PKR) column stays flat by definition - that gap IS the cost of inflation.

Sheet Savings Goal Calculator
B2: Retirement / Goal-Based Savings Calculator
B3: Uses standard time-value-of-money formulas (FV, PMT).
B5: Current age | D5: 30
B6: Target retirement age | D6: 60
B7: Current annual expenses (PKR) | D7: 2760000
B8: Assumed inflation rate (annual) | D8: 0.08
B9: Assumed investment return (nominal, annual) | D9: 0.15
B10: Years of retirement to fund | D10: 20
B11: Current retirement savings (PKR) | D11: 500000
B13: Years Until Retirement | D13: =D6-D5
B14: Annual Expenses at Retirement (inflated) | D14: =D7*(1+D8)^D13
B15: Retirement Corpus Needed (approx., using real annuity) | D15: =D14*(1-(1+((1+D9)/(1+D8)-1))^-D10)/((1+D9)/(1+D8)-1)
B16: Required Monthly Savings (nominal) to Reach Corpus | D16: =-PMT(D9/12,D13*12,D11,D15)

Sheet Dashboard
B2: Inflation Erosion Dashboard
B4: Nominal vs. Real Value of a PKR 1,000,000 Savings Pot (kept in cash/low-yield account at 6% p.a., inflation per 'Inflation Planner' assumption), over 10 years
B7: Year | C7: Nominal Value (6% growth) | D7: Real Value (inflation-adjusted)
B8: 0 | C8: =1000000*(1.06)^B8 | D8: =1000000*(1.06)^B8/(1+'Inflation Planner'!$D$5)^B8
B9: 1 | C9: =1000000*(1.06)^B9 | D9: =1000000*(1.06)^B9/(1+'Inflation Planner'!$D$5)^B9
B10: 2 | C10: =1000000*(1.06)^B10 | D10: =1000000*(1.06)^B10/(1+'Inflation Planner'!$D$5)^B10
B11: 3 | C11: =1000000*(1.06)^B11 | D11: =1000000*(1.06)^B11/(1+'Inflation Planner'!$D$5)^B11
B12: 4 | C12: =1000000*(1.06)^B12 | D12: =1000000*(1.06)^B12/(1+'Inflation Planner'!$D$5)^B12
B13: 5 | C13: =1000000*(1.06)^B13 | D13: =1000000*(1.06)^B13/(1+'Inflation Planner'!$D$5)^B13
B14: 6 | C14: =1000000*(1.06)^B14 | D14: =1000000*(1.06)^B14/(1+'Inflation Planner'!$D$5)^B14
B15: 7 | C15: =1000000*(1.06)^B15 | D15: =1000000*(1.06)^B15/(1+'Inflation Planner'!$D$5)^B15
B16: 8 | C16: =1000000*(1.06)^B16 | D16: =1000000*(1.06)^B16/(1+'Inflation Planner'!$D$5)^B16
B17: 9 | C17: =1000000*(1.06)^B17 | D17: =1000000*(1.06)^B17/(1+'Inflation Planner'!$D$5)^B17
B18: 10 | C18: =1000000*(1.06)^B18 | D18: =1000000*(1.06)^B18/(1+'Inflation Planner'!$D$5)^B18

Sheet Insights
B2: Key Findings & Recommendations
B4: 1. At a 6% nominal return with inflation running near the 10-year historical average, a household's savings pot
B5: can visibly LOSE real purchasing power even as its PKR balance keeps growing - this is the 'money illusion'
B6: problem the Dashboard chart is designed to make immediately visible.
B7: 2. The 'real return needed just to preserve value' calculation in 'Inflation Planner' is the single most useful
B8: number in this workbook for a Pakistani saver: it reframes the question from 'what return am I getting?' to
B9: 'am I actually ahead of inflation?' - a distinction most conventional bank savings products fail on for long
B10: stretches of the last five years (FY2023's ~29% average inflation exceeded almost every conventional deposit rate).
B11: 3. The retirement corpus calculation shows why a fixed monthly savings amount set once and never revisited is
B12: dangerous in Pakistan's inflation environment - the required monthly contribution should be re-run at least
B13: annually as actual inflation and returns diverge from assumptions.
B14: 4. RECOMMENDATION: households should prioritise savings vehicles with a real chance of beating inflation over the
... B16: than 3-5 years away, and reserve pure cash/T-bill instruments for short-term/emergency funds only.
