Workbook

Sheet Read Me
B2: Remittance Corridor Cost Optimizer
B3: A decision-support tool for comparing the true cost of sending money to Pakistan
B6: PURPOSE
B7: Pakistan received an estimated USD 30+ billion in remittances in FY2024 (State Bank of Pakistan), yet the World
B8: Bank's Remittance Prices Worldwide (RPW) database consistently ranks South Asian corridors among the more
B9: expensive in the world - average total cost (fee + FX margin) of sending USD 200 ranges from ~2% to over 7%
B10: depending on channel. Overseas Pakistani workers often pick a channel out of habit rather than by comparing cost,
B11: losing hundreds of dollars a year in avoidable fees and poor exchange rates.
B13: This tool compares Banks, Money Transfer Operators (Western Union, Ria, exchange houses), fintech apps
B14: (Wise, Remitly, Xoom), mobile-wallet-linked transfers (JazzCash/Easypaisa) and the informal hundi/hawala channel
B15: for the three largest corridors into Pakistan by volume: UK, UAE and Saudi Arabia.
B17: HOW TO USE
... B33: / portfolio project, not live quotes. Swap in a live FX-rate API and partner fee feed to make this production-ready.

Sheet Corridor Data
A1: Corridor | B1: Channel | C1: Channel Type | D1: Formal Channel? | E1: Fixed Fee (sender local ccy) | F1: % Fee | G1: FX Margin vs Mid-Market (%) | H1: Delivery Speed | I1: Max Convenient Amount (USD equiv)
A2: UK to Pakistan | B2: High-street Bank Wire | C2: Bank | D2: 1 | E2: 15 | F2: 0.5 | G2: 3.2 | H2: 1-3 business days | I2: 5000
A3: UK to Pakistan | B3: Western Union (Branch) | C3: MTO | D3: 1 | E3: 3.9 | F3: 1.2 | G3: 2.5 | H3: Minutes-1 day | I3: 3000
A4: UK to Pakistan | B4: Ria Money Transfer | C4: MTO | D4: 1 | E4: 2.9 | F4: 0.8 | G4: 2.2 | H4: Minutes-1 day | I4: 3000
A5: UK to Pakistan | B5: Wise | C5: Fintech | D5: 1 | E5: 3.5 | F5: 0.35 | G5: 0.4 | H5: Same day | I5: 5000
A6: UK to Pakistan | B6: Remitly / Xoom Express | C6: Fintech | D6: 1 | E6: 3.99 | F6: 0 | G6: 1.7 | H6: Minutes | I6: 2999
A7: UK to Pakistan | B7: JazzCash / Easypaisa Intl. | C7: Mobile Wallet | D7: 1 | E7: 0 | F7: 1 | G7: 1 | H7: Minutes | I7: 1500
A8: UK to Pakistan | B8: Hundi / Hawala (informal) | C8: Informal | D8: 0 | E8: 0 | F8: 0.5 | G8: 0.3 | H8: Same day | I8: 100000
A9: UAE to Pakistan | B9: High-street Bank Wire | C9: Bank | D9: 1 | E9: 20 | F9: 0.4 | G9: 2.8 | H9: 1-2 business days | I9: 5000
A10: UAE to Pakistan | B10: Western Union (Branch) | C10: MTO | D10: 1 | E10: 15 | F10: 0 | G10: 2 | H10: Minutes-1 day | I10: 3000
A11: UAE to Pakistan | B11: Al Ansari Exchange | C11: MTO | D11: 1 | E11: 10 | F11: 0 | G11: 1.5 | H11: Minutes | I11: 5000
A12: UAE to Pakistan | B12: Wise | C12: Fintech | D12: 1 | E12: 7 | F12: 0.3 | G12: 0.4 | H12: Same day | I12: 5000
A13: UAE to Pakistan | B13: Remitly Express | C13: Fintech | D13: 1 | E13: 3 | F13: 0 | G13: 1.4 | H13: Minutes | I13: 2999
... A22: Saudi Arabia to Pakistan | B22: Hundi / Hawala (informal) | C22: Informal | D22: 0 | E22: 0 | F22: 0.4 | G22: 0.2 | H22: Same day | I22: 100000

Sheet Calculator
B2: Remittance Channel Comparison Calculator
B3: Select a corridor and enter an amount - every channel is ranked by TOTAL cost (fee + FX margin).
B5: Corridor: | C5: UK to Pakistan
B6: Amount to send (sender's local currency): | C6: 500
B8: Corridor start-row lookup (internal):
B9: UK to Pakistan | C9: 2
B10: UAE to Pakistan | C10: 9
B11: Saudi Arabia to Pakistan | C11: 16
B13: Channel | C13: Channel Type | D13: Fixed Fee | E13: % Fee | F13: FX Margin % | G13: Total Cost (amount) | H13: Total Cost % | I13: Amount Received (est.) | J13: Rank (1=cheapest)
B14: =INDEX('Corridor Data'!$B:$B,(VLOOKUP($C$5,$B$9:$C$11,2,FALSE)+0)) | C14: =INDEX('Corridor Data'!$C:$C,(VLOOKUP($C$5,$B$9:$C$11,2,FALSE)+0)) | D14: =INDEX('Corridor Data'!$E:$E,(VLOOKUP($C$5,$B$9:$C$11,2,FALSE)+0)) | E14: =INDEX('Corridor Data'!$F:$F,(VLOOKUP($C$5,$B$9:$C$11,2,FALSE)+0)) | F14: =INDEX('Corridor Data'!$G:$G,(VLOOKUP($C$5,$B$9:$C$11,2,FALSE)+0)) | G14: =D14+(E14/100)*$C$6+(F14/100)*$C$6 | H14: =G14/$C$6 | I14: =$C$6-G14 | J14: =RANK.EQ(G14,$G$14:$G$20,1)
B15: =INDEX('Corridor Data'!$B:$B,(VLOOKUP($C$5,$B$9:$C$11,2,FALSE)+1)) | C15: =INDEX('Corridor Data'!$C:$C,(VLOOKUP($C$5,$B$9:$C$11,2,FALSE)+1)) | D15: =INDEX('Corridor Data'!$E:$E,(VLOOKUP($C$5,$B$9:$C$11,2,FALSE)+1)) | E15: =INDEX('Corridor Data'!$F:$F,(VLOOKUP($C$5,$B$9:$C$11,2,FALSE)+1)) | F15: =INDEX('Corridor Data'!$G:$G,(VLOOKUP($C$5,$B$9:$C$11,2,FALSE)+1)) | G15: =D15+(E15/100)*$C$6+(F15/100)*$C$6 | H15: =G15/$C$6 | I15: =$C$6-G15 | J15: =RANK.EQ(G15,$G$14:$G$20,1)
B16: =INDEX('Corridor Data'!$B:$B,(VLOOKUP($C$5,$B$9:$C$11,2,FALSE)+2)) | C16: =INDEX('Corridor Data'!$C:$C,(VLOOKUP($C$5,$B$9:$C$11,2,FALSE)+2)) | D16: =INDEX('Corridor Data'!$E:$E,(VLOOKUP($C$5,$B$9:$C$11,2,FALSE)+2)) | E16: =INDEX('Corridor Data'!$F:$F,(VLOOKUP($C$5,$B$9:$C$11,2,FALSE)+2)) | F16: =INDEX('Corridor Data'!$G:$G,(VLOOKUP($C$5,$B$9:$C$11,2,FALSE)+2)) | G16: =D16+(E16/100)*$C$6+(F16/100)*$C$6 | H16: =G16/$C$6 | I16: =$C$6-G16 | J16: =RANK.EQ(G16,$G$14:$G$20,1)
B17: =INDEX('Corridor Data'!$B:$B,(VLOOKUP($C$5,$B$9:$C$11,2,FALSE)+3)) | C17: =INDEX('Corridor Data'!$C:$C,(VLOOKUP($C$5,$B$9:$C$11,2,FALSE)+3)) | D17: =INDEX('Corridor Data'!$E:$E,(VLOOKUP($C$5,$B$9:$C$11,2,FALSE)+3)) | E17: =INDEX('Corridor Data'!$F:$F,(VLOOKUP($C$5,$B$9:$C$11,2,FALSE)+3)) | F17: =INDEX('Corridor Data'!$G:$G,(VLOOKUP($C$5,$B$9:$C$11,2,FALSE)+3)) | G17: =D17+(E17/100)*$C$6+(F17/100)*$C$6 | H17: =G17/$C$6 | I17: =$C$6-G17 | J17: =RANK.EQ(G17,$G$14:$G$20,1)
B18: =INDEX('Corridor Data'!$B:$B,(VLOOKUP($C$5,$B$9:$C$11,2,FALSE)+4)) | C18: =INDEX('Corridor Data'!$C:$C,(VLOOKUP($C$5,$B$9:$C$11,2,FALSE)+4)) | D18: =INDEX('Corridor Data'!$E:$E,(VLOOKUP($C$5,$B$9:$C$11,2,FALSE)+4)) | E18: =INDEX('Corridor Data'!$F:$F,(VLOOKUP($C$5,$B$9:$C$11,2,FALSE)+4)) | F18: =INDEX('Corridor Data'!$G:$G,(VLOOKUP($C$5,$B$9:$C$11,2,FALSE)+4)) | G18: =D18+(E18/100)*$C$6+(F18/100)*$C$6 | H18: =G18/$C$6 | I18: =$C$6-G18 | J18: =RANK.EQ(G18,$G$14:$G$20,1)
B19: =INDEX('Corridor Data'!$B:$B,(VLOOKUP($C$5,$B$9:$C$11,2,FALSE)+5)) | C19: =INDEX('Corridor Data'!$C:$C,(VLOOKUP($C$5,$B$9:$C$11,2,FALSE)+5)) | D19: =INDEX('Corridor Data'!$E:$E,(VLOOKUP($C$5,$B$9:$C$11,2,FALSE)+5)) | E19: =INDEX('Corridor Data'!$F:$F,(VLOOKUP($C$5,$B$9:$C$11,2,FALSE)+5)) | F19: =INDEX('Corridor Data'!$G:$G,(VLOOKUP($C$5,$B$9:$C$11,2,FALSE)+5)) | G19: =D19+(E19/100)*$C$6+(F19/100)*$C$6 | H19: =G19/$C$6 | I19: =$C$6-G19 | J19: =RANK.EQ(G19,$G$14:$G$20,1)
B20: =INDEX('Corridor Data'!$B:$B,(VLOOKUP($C$5,$B$9:$C$11,2,FALSE)+6)) | C20: =INDEX('Corridor Data'!$C:$C,(VLOOKUP($C$5,$B$9:$C$11,2,FALSE)+6)) | D20: =INDEX('Corridor Data'!$E:$E,(VLOOKUP($C$5,$B$9:$C$11,2,FALSE)+6)) | E20: =INDEX('Corridor Data'!$F:$F,(VLOOKUP($C$5,$B$9:$C$11,2,FALSE)+6)) | F20: =INDEX('Corridor Data'!$G:$G,(VLOOKUP($C$5,$B$9:$C$11,2,FALSE)+6)) | G20: =D20+(E20/100)*$C$6+(F20/100)*$C$6 | H20: =G20/$C$6 | I20: =$C$6-G20 | J20: =RANK.EQ(G20,$G$14:$G$20,1)
B22: Cheapest Channel: | C22: =INDEX($B14:$B20,MATCH(1,$J14:$J20,0))
B23: Cheapest Total Cost: | C23: =MIN($G14:$G20)
B24: Most Expensive Total Cost: | C24: =MAX($G14:$G20)
B25: Potential Annual Savings (12 transfers, cheapest vs. costliest): | C25: =(C24-C23)*12

Sheet Dashboard
B2: Cost Analysis Dashboard
B4: Average Total Cost (%) to send an equivalent of USD 500, by channel type (all 3 corridors)
B5: Channel Type | C5: Avg Total Cost %
B6: Bank | C6: 7.43
B7: MTO | C7: 4.09
B8: Fintech | C8: 2.22
B9: Mobile Wallet | C9: 1.87
B10: Informal | C10: 0.63
B20: Cost as % of Amount Sent - Economies of Scale (UK to Pakistan corridor)
B21: Amount Sent (GBP) | C21: High-street Bank | D21: Western Union | E21: Wise (fintech) | F21: Hundi (informal)
B22: 100 | C22: 18.7 | D22: 7.6 | E22: 4.25 | F22: 0.8
B23: 250 | C23: 9.7 | D23: 5.26 | E23: 2.15 | F23: 0.8
B24: 500 | C24: 6.7 | D24: 4.48 | E24: 1.45 | F24: 0.8
B25: 1000 | C25: 5.2 | D25: 4.09 | E25: 1.1 | F25: 0.8
B26: 2000 | C26: 4.45 | D26: 3.9 | E26: 0.92 | F26: 0.8
B27: 5000 | C27: 4 | D27: 3.78 | E27: 0.82 | F27: 0.8

Sheet Insights
B2: Key Findings & Recommendations
B4: 1. Fintech apps (Wise) are consistently the cheapest formal option once the amount sent exceeds ~GBP 250, because
B5: their FX margin (0.3-0.5%) is far below banks and MTOs (1.5-3.2%), even though banks advertise 'free transfers'.
B6: 2. For very small transfers (under GBP 100), fixed fees dominate - mobile-wallet-linked transfers (JazzCash/
B7: Easypaisa) can beat fintech apps because there is no fixed fee to amortise over a small amount.
B8: 3. Banks are the single most expensive formal channel across all three corridors once fee + FX margin are combined,
B9: despite being perceived by senders as the 'safe default' option - a clear information gap this tool addresses.
B10: 4. Informal hundi/hawala channels remain cost-competitive (low fee, near-mid-market FX), which helps explain why an
B11: estimated 30-40% of Pakistan's remittance flows are believed to bypass formal channels (SBP / World Bank
B12: estimates) - a policy problem, since informal flows are unregulated, offer no consumer protection, and are
B13: undocumented for GDP, tax, and monetary-policy purposes.
B14: 5. CONSUMER RECOMMENDATION: switch to a licensed fintech remittance app for transfers above GBP/AED/SAR 250-300;
... B21: sites for money transfer.
