Workbook

Sheet Read Me
B2: Fintech Startup 3-Statement Model & DCF Valuation
B3: 'PaySetu' - a hypothetical Pakistani BNPL/digital-lending startup: fully linked 5-year financial model + valuation
B5: PURPOSE
B6: Every fintech lender or BNPL (buy-now-pay-later) startup faces the same structural challenge that makes it
B7: different from a typical SaaS or e-commerce business: to grow revenue, it must fund a growing book of customer
B8: receivables on its own balance sheet, which consumes far more cash than an ordinary working-capital cycle -
B9: and that cash need has to be modelled explicitly, or a founder/analyst will badly misjudge how much funding the
B10: business actually needs and when. This project builds a fully linked 3-statement model (Income Statement,
B11: Balance Sheet, Cash Flow Statement) for a hypothetical Pakistani BNPL startup, 'PaySetu', and then values it
B12: with a discounted cash flow (DCF) approach adapted correctly for a balance-sheet-heavy lending business.
B14: HOW THE MODEL IS BUILT
B15: 1. 'Assumptions' - every driver (user growth, revenue take rate, cost of funds, opex, capex, financing) in one
... B45: Pakistan's historically high interest-rate environment, not live market data.

Sheet Assumptions
B2: Model Assumptions - PaySetu (Hypothetical Pakistani BNPL Fintech)
B4: Driver | C4: Year 1 | D4: Year 2 | E4: Year 3 | F4: Year 4 | G4: Year 5
B5: Active Users (period end) | C5: 50000 | D5: 180000 | E5: 450000 | F5: 850000 | G5: 1500000
B6: New Users Acquired | C6: 50000 | D6: 130000 | E6: 270000 | F6: 400000 | G6: 650000
B7: Annual GMV per Active User (PKR) | C7: 8000 | D7: 9000 | E7: 10000 | F7: 11000 | G7: 12000
B8: Take Rate (Revenue % of GMV) | C8: 0.06 | D8: 0.065 | E8: 0.07 | F8: 0.072 | G8: 0.075
B9: Cost of Funds Rate (annual, on receivables balance) | C9: 0.16 | D9: 0.15 | E9: 0.14 | F9: 0.13 | G9: 0.12
B10: Marketing Cost per New User (PKR) | C10: 700 | D10: 550 | E10: 450 | F10: 380 | G10: 320
B11: Tech + G&A Cost (PKR) | C11: 35000000 | D11: 55000000 | E11: 80000000 | F11: 110000000 | G11: 145000000
B12: Receivables Days Outstanding | C12: 25 | D12: 25 | E12: 25 | F12: 25 | G12: 25
B13: Payables (% of Opex) | C13: 0.1 | D13: 0.1 | E13: 0.1 | F13: 0.1 | G13: 0.1
B14: Capex (PKR) | C14: 12000000 | D14: 16000000 | E14: 20000000 | F14: 24000000 | G14: 28000000
B15: Warehouse Debt Advance Rate (% of Receivables) | C15: 0.85 | D15: 0.85 | E15: 0.85 | F15: 0.85 | G15: 0.85
B16: New Equity Raised (PKR) | C16: 90000000 | D16: 70000000 | E16: 60000000 | F16: 0 | G16: 0
B18: Single-Value Assumptions
B19: Depreciation Life (years, straight-line) | C19: 4
B20: Corporate Tax Rate | C20: 0.29
B21: Cost of Debt (annual interest rate) | C21: 0.16
B22: Risk-Free Rate (Rf, PKR long bond proxy) | C22: 0.12
B23: Equity Beta (fintech growth-stage proxy) | C23: 1.3
B24: Equity Risk Premium (Pakistan, illustrative) | C24: 0.08
B25: Terminal Growth Rate (perpetuity, nominal PKR) | C25: 0.08
B26: Shares Outstanding (illustrative cap table, millions) | C26: 10
B27: Cost of Equity (CAPM: Rf + Beta x ERP) | C27: =C22+C23*C24

Sheet Income Statement
B2: Income Statement (PKR)
B4: Line Item | C4: Year 1 | D4: Year 2 | E4: Year 3 | F4: Year 4 | G4: Year 5
B5: Gross Merchandise/Loan Value (GMV) | C5: =Assumptions!C5*Assumptions!C7 | D5: =Assumptions!D5*Assumptions!D7 | E5: =Assumptions!E5*Assumptions!E7 | F5: =Assumptions!F5*Assumptions!F7 | G5: =Assumptions!G5*Assumptions!G7
B6: Revenue (Take Rate x GMV) | C6: =C5*Assumptions!C8 | D6: =D5*Assumptions!D8 | E6: =E5*Assumptions!E8 | F6: =F5*Assumptions!F8 | G6: =G5*Assumptions!G8
B7: Receivables Balance (GMV x Days/365) | C7: =C5*Assumptions!C12/365 | D7: =D5*Assumptions!D12/365 | E7: =E5*Assumptions!E12/365 | F7: =F5*Assumptions!F12/365 | G7: =G5*Assumptions!G12/365
B8: Funding Cost (Cost of Funds x Receivables) | C8: =C7*Assumptions!C9 | D8: =D7*Assumptions!D9 | E8: =E7*Assumptions!E9 | F8: =F7*Assumptions!F9 | G8: =G7*Assumptions!G9
B9: Gross Profit | C9: =C6-C8 | D9: =D6-D8 | E9: =E6-E8 | F9: =F6-F8 | G9: =G6-G8
B10: Marketing / Customer Acquisition Cost | C10: =Assumptions!C6*Assumptions!C10 | D10: =Assumptions!D6*Assumptions!D10 | E10: =Assumptions!E6*Assumptions!E10 | F10: =Assumptions!F6*Assumptions!F10 | G10: =Assumptions!G6*Assumptions!G10
B11: Technology + G&A Cost | C11: =Assumptions!C11 | D11: =Assumptions!D11 | E11: =Assumptions!E11 | F11: =Assumptions!F11 | G11: =Assumptions!G11
B12: Total Opex | C12: =C10+C11 | D12: =D10+D11 | E12: =E10+E11 | F12: =F10+F11 | G12: =G10+G11
B13: EBITDA | C13: =C9-C12 | D13: =D9-D12 | E13: =E9-E12 | F13: =F9-F12 | G13: =G9-G12
B14: Depreciation & Amortisation | C14: =IF((0-0)<Assumptions!$C$19,Assumptions!C14/Assumptions!$C$19,0) | D14: =IF((1-0)<Assumptions!$C$19,Assumptions!C14/Assumptions!$C$19,0)+IF((1-1)<Assumptions!$C$19,Assumptions!D14/Assumptions!$C$19,0) | E14: =IF((2-0)<Assumptions!$C$19,Assumptions!C14/Assumptions!$C$19,0)+IF((2-1)<Assumptions!$C$19,Assumptions!D14/Assumptions!$C$19,0)+IF((2-2)<Assumptions!$C$19,Assumptions!E14/Assumptions!$C$19,0) | F14: =IF((3-0)<Assumptions!$C$19,Assumptions!C14/Assumptions!$C$19,0)+IF((3-1)<Assumptions!$C$19,Assumptions!D14/Assumptions!$C$19,0)+IF((3-2)<Assumptions!$C$19,Assumptions!E14/Assumptions!$C$19,0)+IF((3-3)<Assumptions!$C$19,Assumptions!F14/Assumptions!$C$19,0) | G14: =IF((4-0)<Assumptions!$C$19,Assumptions!C14/Assumptions!$C$19,0)+IF((4-1)<Assumptions!$C$19,Assumptions!D14/Assumptions!$C$19,0)+IF((4-2)<Assumptions!$C$19,Assumptions!E14/Assumptions!$C$19,0)+IF((4-3)<Assumptions!$C$19,Assumptions!F14/Assumptions!$C$19,0)+IF((4-4)<Assumptions!$C$19,Assumptions!G14/Assumptions!$C$19,0)
B15: EBIT | C15: =C13-C14 | D15: =D13-D14 | E15: =E13-E14 | F15: =F13-F14 | G15: =G13-G14
B16: PP&E, Net (memo - rolled forward here for Balance Sheet) | C16: =0+Assumptions!C14-C14 | D16: =C16+Assumptions!D14-D14 | E16: =D16+Assumptions!E14-E14 | F16: =E16+Assumptions!F14-F14 | G16: =F16+Assumptions!G14-G14
B17: Debt Balance (memo - Warehouse Facility, % of Receivables) | C17: =C7*Assumptions!C15 | D17: =D7*Assumptions!D15 | E17: =E7*Assumptions!E15 | F17: =F7*Assumptions!F15 | G17: =G7*Assumptions!G15
B18: Interest Expense (on opening debt balance) | C18: =0*Assumptions!$C$21 | D18: =C17*Assumptions!$C$21 | E18: =D17*Assumptions!$C$21 | F18: =E17*Assumptions!$C$21 | G18: =F17*Assumptions!$C$21
B19: EBT (Pre-Tax Income) | C19: =C15-C18 | D19: =D15-D18 | E19: =E15-E18 | F19: =F15-F18 | G19: =G15-G18
B20: Tax (on positive EBT only) | C20: =MAX(0,C19)*Assumptions!$C$20 | D20: =MAX(0,D19)*Assumptions!$C$20 | E20: =MAX(0,E19)*Assumptions!$C$20 | F20: =MAX(0,F19)*Assumptions!$C$20 | G20: =MAX(0,G19)*Assumptions!$C$20
B21: NET INCOME | C21: =C19-C20 | D21: =D19-D20 | E21: =E19-E20 | F21: =F19-F20 | G21: =G19-G20

Sheet Balance Sheet
B2: Balance Sheet (PKR)
B4: Line Item | C4: Year 1 | D4: Year 2 | E4: Year 3 | F4: Year 4 | G4: Year 5
B5: ASSETS
B6: Cash | C6: ='Cash Flow Statement'!C22 | D6: ='Cash Flow Statement'!D22 | E6: ='Cash Flow Statement'!E22 | F6: ='Cash Flow Statement'!F22 | G6: ='Cash Flow Statement'!G22
B7: Receivables | C7: ='Income Statement'!C7 | D7: ='Income Statement'!D7 | E7: ='Income Statement'!E7 | F7: ='Income Statement'!F7 | G7: ='Income Statement'!G7
B8: PP&E, Net | C8: ='Income Statement'!C16 | D8: ='Income Statement'!D16 | E8: ='Income Statement'!E16 | F8: ='Income Statement'!F16 | G8: ='Income Statement'!G16
B9: TOTAL ASSETS | C9: =C6+C7+C8 | D9: =D6+D7+D8 | E9: =E6+E7+E8 | F9: =F6+F7+F8 | G9: =G6+G7+G8
B11: LIABILITIES
B12: Payables | C12: ='Income Statement'!C12*Assumptions!C13 | D12: ='Income Statement'!D12*Assumptions!D13 | E12: ='Income Statement'!E12*Assumptions!E13 | F12: ='Income Statement'!F12*Assumptions!F13 | G12: ='Income Statement'!G12*Assumptions!G13
B13: Debt (Warehouse Facility) | C13: ='Income Statement'!C17 | D13: ='Income Statement'!D17 | E13: ='Income Statement'!E17 | F13: ='Income Statement'!F17 | G13: ='Income Statement'!G17
B14: TOTAL LIABILITIES | C14: =C12+C13 | D14: =D12+D13 | E14: =E12+E13 | F14: =F12+F13 | G14: =G12+G13
B16: EQUITY
B17: Share Capital (Cumulative Equity Raised) | C17: =0+Assumptions!C16 | D17: =C17+Assumptions!D16 | E17: =D17+Assumptions!E16 | F17: =E17+Assumptions!F16 | G17: =F17+Assumptions!G16
B18: Retained Earnings (Cumulative Net Income) | C18: =0+'Income Statement'!C21 | D18: =C18+'Income Statement'!D21 | E18: =D18+'Income Statement'!E21 | F18: =E18+'Income Statement'!F21 | G18: =F18+'Income Statement'!G21
B19: TOTAL EQUITY | C19: =C17+C18 | D19: =D17+D18 | E19: =E17+E18 | F19: =F17+F18 | G19: =G17+G18
B21: CHECK: Total Assets - (Total Liab + Total Equity) | C21: =C9-(C14+C19) | D21: =D9-(D14+D19) | E21: =E9-(E14+E19) | F21: =F9-(F14+F19) | G21: =G9-(G14+G19)

Sheet Cash Flow Statement
B2: Cash Flow Statement (PKR)
B4: Line Item | C4: Year 1 | D4: Year 2 | E4: Year 3 | F4: Year 4 | G4: Year 5
B5: OPERATING ACTIVITIES
B6: Net Income | C6: ='Income Statement'!C21 | D6: ='Income Statement'!D21 | E6: ='Income Statement'!E21 | F6: ='Income Statement'!F21 | G6: ='Income Statement'!G21
B7: Add: Depreciation & Amortisation | C7: ='Income Statement'!C14 | D7: ='Income Statement'!D14 | E7: ='Income Statement'!E14 | F7: ='Income Statement'!F14 | G7: ='Income Statement'!G14
B8: Less: Increase in Receivables | C8: =-('Balance Sheet'!C7-0) | D8: =-('Balance Sheet'!D7-'Balance Sheet'!C7) | E8: =-('Balance Sheet'!E7-'Balance Sheet'!D7) | F8: =-('Balance Sheet'!F7-'Balance Sheet'!E7) | G8: =-('Balance Sheet'!G7-'Balance Sheet'!F7)
B9: Add: Increase in Payables | C9: ='Balance Sheet'!C12-0 | D9: ='Balance Sheet'!D12-'Balance Sheet'!C12 | E9: ='Balance Sheet'!E12-'Balance Sheet'!D12 | F9: ='Balance Sheet'!F12-'Balance Sheet'!E12 | G9: ='Balance Sheet'!G12-'Balance Sheet'!F12
B10: CASH FLOW FROM OPERATIONS (CFO) | C10: =C6+C7+C8+C9 | D10: =D6+D7+D8+D9 | E10: =E6+E7+E8+E9 | F10: =F6+F7+F8+F9 | G10: =G6+G7+G8+G9
B12: INVESTING ACTIVITIES
B13: Capex | C13: =-Assumptions!C14 | D13: =-Assumptions!D14 | E13: =-Assumptions!E14 | F13: =-Assumptions!F14 | G13: =-Assumptions!G14
B15: FINANCING ACTIVITIES
B16: Net Debt Drawn (Warehouse Facility) | C16: ='Balance Sheet'!C13-0 | D16: ='Balance Sheet'!D13-'Balance Sheet'!C13 | E16: ='Balance Sheet'!E13-'Balance Sheet'!D13 | F16: ='Balance Sheet'!F13-'Balance Sheet'!E13 | G16: ='Balance Sheet'!G13-'Balance Sheet'!F13
B17: New Equity Raised | C17: =Assumptions!C16 | D17: =Assumptions!D16 | E17: =Assumptions!E16 | F17: =Assumptions!F16 | G17: =Assumptions!G16
B18: CASH FLOW FROM FINANCING (CFF) | C18: =C16+C17 | D18: =D16+D17 | E18: =E16+E17 | F18: =F16+F17 | G18: =G16+G17
B20: NET CHANGE IN CASH | C20: =C10+C13+C18 | D20: =D10+D13+D18 | E20: =E10+E13+E18 | F20: =F10+F13+F18 | G20: =G10+G13+G18
B21: Beginning Cash | C21: =0 | D21: =C22 | E21: =D22 | F21: =E22 | G21: =F22
B22: ENDING CASH | C22: =C21+C20 | D22: =D21+D20 | E22: =E21+E20 | F22: =F21+F20 | G22: =G21+G20

Sheet DCF Valuation
B2: DCF Valuation - Free Cash Flow to Equity (FCFE) Approach
B3: See 'Read Me' for why FCFE (discounted at Cost of Equity) is used instead of a standard unlevered FCF/WACC DCF for this lending business.
B5: Line Item | C5: Year 1 | D5: Year 2 | E5: Year 3 | F5: Year 4 | G5: Year 5
B6: Net Income | C6: ='Income Statement'!C21 | D6: ='Income Statement'!D21 | E6: ='Income Statement'!E21 | F6: ='Income Statement'!F21 | G6: ='Income Statement'!G21
B7: Add: D&A | C7: ='Income Statement'!C14 | D7: ='Income Statement'!D14 | E7: ='Income Statement'!E14 | F7: ='Income Statement'!F14 | G7: ='Income Statement'!G14
B8: Less: Capex | C8: =-Assumptions!C14 | D8: =-Assumptions!D14 | E8: =-Assumptions!E14 | F8: =-Assumptions!F14 | G8: =-Assumptions!G14
B9: Less: Increase in Net Working Capital (Receivables - Payables) | C9: ='Cash Flow Statement'!C8+'Cash Flow Statement'!C9 | D9: ='Cash Flow Statement'!D8+'Cash Flow Statement'!D9 | E9: ='Cash Flow Statement'!E8+'Cash Flow Statement'!E9 | F9: ='Cash Flow Statement'!F8+'Cash Flow Statement'!F9 | G9: ='Cash Flow Statement'!G8+'Cash Flow Statement'!G9
B10: Add: Net Debt Drawn (Warehouse Facility) | C10: ='Cash Flow Statement'!C16 | D10: ='Cash Flow Statement'!D16 | E10: ='Cash Flow Statement'!E16 | F10: ='Cash Flow Statement'!F16 | G10: ='Cash Flow Statement'!G16
B11: FREE CASH FLOW TO EQUITY (FCFE) | C11: =C6+C7+C8+C9+C10 | D11: =D6+D7+D8+D9+D10 | E11: =E6+E7+E8+E9+E10 | F11: =F6+F7+F8+F9+F10 | G11: =G6+G7+G8+G9+G10
B13: Discount Factor (at Cost of Equity) | C13: =1/(1+Assumptions!$C$27)^1 | D13: =1/(1+Assumptions!$C$27)^2 | E13: =1/(1+Assumptions!$C$27)^3 | F13: =1/(1+Assumptions!$C$27)^4 | G13: =1/(1+Assumptions!$C$27)^5
B14: PV of FCFE | C14: =C11*C13 | D14: =D11*D13 | E14: =E11*E13 | F14: =F11*F13 | G14: =G11*G13
B16: Sum of PV of FCFE (Years 1-5) | D16: =SUM(C14:G14)
B17: Terminal Value (Gordon Growth, at end of Year 5) | D17: =G11*(1+Assumptions!$C$25)/(Assumptions!$C$27-Assumptions!$C$25)
B18: PV of Terminal Value | D18: =D17*G13
B19: EQUITY VALUE (PV of FCFE + PV of Terminal Value) | D19: =D16+D18
B20: Implied Value per Share (PKR) | D20: =D19/(Assumptions!$C$26*1000000)
B22: Cost of Equity Used (from Assumptions) | D22: =Assumptions!$C$27

Sheet Sensitivity
B2: Sensitivity: Equity Value (PKR) - Cost of Equity vs. Terminal Growth
B3: Each cell independently recomputes Sum of PV(FCFE) + PV(Terminal Value) for that Cost of Equity / growth pair.
B5: Cost of Equity ↓ / Terminal Growth → | C5: 0.04 | D5: 0.06 | E5: 0.08 | F5: 0.1 | G5: 0.12
B6: 0.184 | C6: ='DCF Valuation'!C$11/(1+$B6)^1+'DCF Valuation'!D$11/(1+$B6)^2+'DCF Valuation'!E$11/(1+$B6)^3+'DCF Valuation'!F$11/(1+$B6)^4+'DCF Valuation'!G$11/(1+$B6)^5+('DCF Valuation'!$G$11*(1+C$5)/($B6-C$5))/(1+$B6)^5 | D6: ='DCF Valuation'!C$11/(1+$B6)^1+'DCF Valuation'!D$11/(1+$B6)^2+'DCF Valuation'!E$11/(1+$B6)^3+'DCF Valuation'!F$11/(1+$B6)^4+'DCF Valuation'!G$11/(1+$B6)^5+('DCF Valuation'!$G$11*(1+D$5)/($B6-D$5))/(1+$B6)^5 | E6: ='DCF Valuation'!C$11/(1+$B6)^1+'DCF Valuation'!D$11/(1+$B6)^2+'DCF Valuation'!E$11/(1+$B6)^3+'DCF Valuation'!F$11/(1+$B6)^4+'DCF Valuation'!G$11/(1+$B6)^5+('DCF Valuation'!$G$11*(1+E$5)/($B6-E$5))/(1+$B6)^5 | F6: ='DCF Valuation'!C$11/(1+$B6)^1+'DCF Valuation'!D$11/(1+$B6)^2+'DCF Valuation'!E$11/(1+$B6)^3+'DCF Valuation'!F$11/(1+$B6)^4+'DCF Valuation'!G$11/(1+$B6)^5+('DCF Valuation'!$G$11*(1+F$5)/($B6-F$5))/(1+$B6)^5 | G6: ='DCF Valuation'!C$11/(1+$B6)^1+'DCF Valuation'!D$11/(1+$B6)^2+'DCF Valuation'!E$11/(1+$B6)^3+'DCF Valuation'!F$11/(1+$B6)^4+'DCF Valuation'!G$11/(1+$B6)^5+('DCF Valuation'!$G$11*(1+G$5)/($B6-G$5))/(1+$B6)^5
B7: 0.204 | C7: ='DCF Valuation'!C$11/(1+$B7)^1+'DCF Valuation'!D$11/(1+$B7)^2+'DCF Valuation'!E$11/(1+$B7)^3+'DCF Valuation'!F$11/(1+$B7)^4+'DCF Valuation'!G$11/(1+$B7)^5+('DCF Valuation'!$G$11*(1+C$5)/($B7-C$5))/(1+$B7)^5 | D7: ='DCF Valuation'!C$11/(1+$B7)^1+'DCF Valuation'!D$11/(1+$B7)^2+'DCF Valuation'!E$11/(1+$B7)^3+'DCF Valuation'!F$11/(1+$B7)^4+'DCF Valuation'!G$11/(1+$B7)^5+('DCF Valuation'!$G$11*(1+D$5)/($B7-D$5))/(1+$B7)^5 | E7: ='DCF Valuation'!C$11/(1+$B7)^1+'DCF Valuation'!D$11/(1+$B7)^2+'DCF Valuation'!E$11/(1+$B7)^3+'DCF Valuation'!F$11/(1+$B7)^4+'DCF Valuation'!G$11/(1+$B7)^5+('DCF Valuation'!$G$11*(1+E$5)/($B7-E$5))/(1+$B7)^5 | F7: ='DCF Valuation'!C$11/(1+$B7)^1+'DCF Valuation'!D$11/(1+$B7)^2+'DCF Valuation'!E$11/(1+$B7)^3+'DCF Valuation'!F$11/(1+$B7)^4+'DCF Valuation'!G$11/(1+$B7)^5+('DCF Valuation'!$G$11*(1+F$5)/($B7-F$5))/(1+$B7)^5 | G7: ='DCF Valuation'!C$11/(1+$B7)^1+'DCF Valuation'!D$11/(1+$B7)^2+'DCF Valuation'!E$11/(1+$B7)^3+'DCF Valuation'!F$11/(1+$B7)^4+'DCF Valuation'!G$11/(1+$B7)^5+('DCF Valuation'!$G$11*(1+G$5)/($B7-G$5))/(1+$B7)^5
B8: 0.224 | C8: ='DCF Valuation'!C$11/(1+$B8)^1+'DCF Valuation'!D$11/(1+$B8)^2+'DCF Valuation'!E$11/(1+$B8)^3+'DCF Valuation'!F$11/(1+$B8)^4+'DCF Valuation'!G$11/(1+$B8)^5+('DCF Valuation'!$G$11*(1+C$5)/($B8-C$5))/(1+$B8)^5 | D8: ='DCF Valuation'!C$11/(1+$B8)^1+'DCF Valuation'!D$11/(1+$B8)^2+'DCF Valuation'!E$11/(1+$B8)^3+'DCF Valuation'!F$11/(1+$B8)^4+'DCF Valuation'!G$11/(1+$B8)^5+('DCF Valuation'!$G$11*(1+D$5)/($B8-D$5))/(1+$B8)^5 | E8: ='DCF Valuation'!C$11/(1+$B8)^1+'DCF Valuation'!D$11/(1+$B8)^2+'DCF Valuation'!E$11/(1+$B8)^3+'DCF Valuation'!F$11/(1+$B8)^4+'DCF Valuation'!G$11/(1+$B8)^5+('DCF Valuation'!$G$11*(1+E$5)/($B8-E$5))/(1+$B8)^5 | F8: ='DCF Valuation'!C$11/(1+$B8)^1+'DCF Valuation'!D$11/(1+$B8)^2+'DCF Valuation'!E$11/(1+$B8)^3+'DCF Valuation'!F$11/(1+$B8)^4+'DCF Valuation'!G$11/(1+$B8)^5+('DCF Valuation'!$G$11*(1+F$5)/($B8-F$5))/(1+$B8)^5 | G8: ='DCF Valuation'!C$11/(1+$B8)^1+'DCF Valuation'!D$11/(1+$B8)^2+'DCF Valuation'!E$11/(1+$B8)^3+'DCF Valuation'!F$11/(1+$B8)^4+'DCF Valuation'!G$11/(1+$B8)^5+('DCF Valuation'!$G$11*(1+G$5)/($B8-G$5))/(1+$B8)^5
B9: 0.244 | C9: ='DCF Valuation'!C$11/(1+$B9)^1+'DCF Valuation'!D$11/(1+$B9)^2+'DCF Valuation'!E$11/(1+$B9)^3+'DCF Valuation'!F$11/(1+$B9)^4+'DCF Valuation'!G$11/(1+$B9)^5+('DCF Valuation'!$G$11*(1+C$5)/($B9-C$5))/(1+$B9)^5 | D9: ='DCF Valuation'!C$11/(1+$B9)^1+'DCF Valuation'!D$11/(1+$B9)^2+'DCF Valuation'!E$11/(1+$B9)^3+'DCF Valuation'!F$11/(1+$B9)^4+'DCF Valuation'!G$11/(1+$B9)^5+('DCF Valuation'!$G$11*(1+D$5)/($B9-D$5))/(1+$B9)^5 | E9: ='DCF Valuation'!C$11/(1+$B9)^1+'DCF Valuation'!D$11/(1+$B9)^2+'DCF Valuation'!E$11/(1+$B9)^3+'DCF Valuation'!F$11/(1+$B9)^4+'DCF Valuation'!G$11/(1+$B9)^5+('DCF Valuation'!$G$11*(1+E$5)/($B9-E$5))/(1+$B9)^5 | F9: ='DCF Valuation'!C$11/(1+$B9)^1+'DCF Valuation'!D$11/(1+$B9)^2+'DCF Valuation'!E$11/(1+$B9)^3+'DCF Valuation'!F$11/(1+$B9)^4+'DCF Valuation'!G$11/(1+$B9)^5+('DCF Valuation'!$G$11*(1+F$5)/($B9-F$5))/(1+$B9)^5 | G9: ='DCF Valuation'!C$11/(1+$B9)^1+'DCF Valuation'!D$11/(1+$B9)^2+'DCF Valuation'!E$11/(1+$B9)^3+'DCF Valuation'!F$11/(1+$B9)^4+'DCF Valuation'!G$11/(1+$B9)^5+('DCF Valuation'!$G$11*(1+G$5)/($B9-G$5))/(1+$B9)^5
B10: 0.264 | C10: ='DCF Valuation'!C$11/(1+$B10)^1+'DCF Valuation'!D$11/(1+$B10)^2+'DCF Valuation'!E$11/(1+$B10)^3+'DCF Valuation'!F$11/(1+$B10)^4+'DCF Valuation'!G$11/(1+$B10)^5+('DCF Valuation'!$G$11*(1+C$5)/($B10-C$5))/(1+$B10)^5 | D10: ='DCF Valuation'!C$11/(1+$B10)^1+'DCF Valuation'!D$11/(1+$B10)^2+'DCF Valuation'!E$11/(1+$B10)^3+'DCF Valuation'!F$11/(1+$B10)^4+'DCF Valuation'!G$11/(1+$B10)^5+('DCF Valuation'!$G$11*(1+D$5)/($B10-D$5))/(1+$B10)^5 | E10: ='DCF Valuation'!C$11/(1+$B10)^1+'DCF Valuation'!D$11/(1+$B10)^2+'DCF Valuation'!E$11/(1+$B10)^3+'DCF Valuation'!F$11/(1+$B10)^4+'DCF Valuation'!G$11/(1+$B10)^5+('DCF Valuation'!$G$11*(1+E$5)/($B10-E$5))/(1+$B10)^5 | F10: ='DCF Valuation'!C$11/(1+$B10)^1+'DCF Valuation'!D$11/(1+$B10)^2+'DCF Valuation'!E$11/(1+$B10)^3+'DCF Valuation'!F$11/(1+$B10)^4+'DCF Valuation'!G$11/(1+$B10)^5+('DCF Valuation'!$G$11*(1+F$5)/($B10-F$5))/(1+$B10)^5 | G10: ='DCF Valuation'!C$11/(1+$B10)^1+'DCF Valuation'!D$11/(1+$B10)^2+'DCF Valuation'!E$11/(1+$B10)^3+'DCF Valuation'!F$11/(1+$B10)^4+'DCF Valuation'!G$11/(1+$B10)^5+('DCF Valuation'!$G$11*(1+G$5)/($B10-G$5))/(1+$B10)^5

Sheet Dashboard
B2: Financial Summary Dashboard
B4: Year | C4: Year 1 | D4: Year 2 | E4: Year 3 | F4: Year 4 | G4: Year 5
B5: Revenue | C5: ='Income Statement'!C6 | D5: ='Income Statement'!D6 | E5: ='Income Statement'!E6 | F5: ='Income Statement'!F6 | G5: ='Income Statement'!G6
B6: EBITDA | C6: ='Income Statement'!C13 | D6: ='Income Statement'!D13 | E6: ='Income Statement'!E13 | F6: ='Income Statement'!F13 | G6: ='Income Statement'!G13
B7: Net Income | C7: ='Income Statement'!C21 | D7: ='Income Statement'!D21 | E7: ='Income Statement'!E21 | F7: ='Income Statement'!F21 | G7: ='Income Statement'!G21

Sheet Insights
B2: Key Findings & Recommendations
B4: 1. THE MODEL SHOWS A CLASSIC FINTECH J-CURVE: EBITDA is negative in Years 1-2 (customer acquisition and cost-of-
B5: funds outweigh a still-small revenue base), turns positive in Year 3, and scales to a healthy margin by Year 5
B6: as fixed tech/G&A costs are spread over a much larger revenue base (operating leverage).
B7: 2. THE BALANCE SHEET CHECK ROW HOLDS AT ZERO IN EVERY YEAR BY FORMULA - proof that all three statements are
B8: properly double-entry linked (Net Income flows to Retained Earnings, cash flow reconciles to the Balance
B9: Sheet's cash balance, and every asset is matched by a liability or equity claim) rather than hand-plugged.
B10: 3. A NAIVE UNLEVERED-FCF DCF WOULD MISVALUE THIS BUSINESS: because receivables scale directly with GMV growth,
B11: an unlevered FCF calculation (which assumes the receivables build is equity/blended-capital funded) produces a
B12: deeply negative, nonsensical enterprise value. Recognising that the receivables are matched-funded by the
B13: warehouse debt facility, and valuing on a FREE CASH FLOW TO EQUITY basis instead, resolves this and produces a
B14: sensible positive equity value - the single most important modelling judgment call in this project.
... B20: the terminal-value assumption deserves the most scrutiny in any DCF, not the discount rate.
