Workbook

Sheet Read Me
B2: Microfinance Loan Default Risk Prediction Model
B3: A logistic-regression credit-risk model for microfinance lending, fully embedded as live spreadsheet formulas
B5: PURPOSE
B6: Microfinance institutions (MFIs) in Pakistan - Akhuwat, Kashf Foundation, FINCA Pakistan, National Rural
B7: Support Programme (NRSP) Microfinance Bank, and others - extend small, often uncollateralised loans to low-
B8: income borrowers who have no access to conventional banking. Because loan sizes are small and volumes are high,
B9: MFIs cannot afford a manual credit-committee review for every applicant the way a commercial bank does for a
B10: large corporate loan - they need a fast, statistically grounded, and auditable way to estimate default risk from
B11: a handful of application-time variables.
B13: THE MODEL
B14: This workbook fits a LOGISTIC REGRESSION (the industry-standard technique for binary credit-risk prediction,
B15: used in real Basel-style probability-of-default models) on 200 synthetic microfinance loans using 8 predictors:
... B39: is the same one used in real microfinance and consumer-credit risk teams.

Sheet Model Coefficients
B2: Fitted Logistic Regression Coefficients
B3: Fitted offline (scikit-learn) on standardised predictors; embedded here for live scoring.
B5: Variable | C5: Coefficient (log-odds, standardised) | D5: Odds Ratio (e^coef) | E5: Direction of Effect
B6: Intercept | C6: -1.7502
B7: Loan Amount (PKR '000) | C7: 0.8979 | D7: =EXP(C7) | E7: Larger loan amount -> strongly HIGHER predicted default risk (fitted coef. +0.898)
B8: Loan Term (months) | C8: 0.1523 | D8: =EXP(C8) | E8: Longer loan term -> only slightly HIGHER predicted default risk (fitted coef. +0.152)
B9: Borrower Age | C9: 0.5196 | D9: =EXP(C9) | E9: Older borrower -> moderately HIGHER predicted default risk (fitted coef. +0.520)
B10: Monthly Income (PKR '000) | C10: -1.0894 | D10: =EXP(C10) | E10: Higher monthly income -> strongly LOWER predicted default risk (fitted coef. -1.089)
B11: Dependents | C11: 0.4237 | D11: =EXP(C11) | E11: More dependents -> moderately HIGHER predicted default risk (fitted coef. +0.424)
B12: Previous Loans Completed | C12: -0.1231 | D12: =EXP(C12) | E12: More prior loans completed -> only slightly LOWER predicted default risk (fitted coef. -0.123)
B13: Group Lending (1/0) | C13: -0.3256 | D13: =EXP(C13) | E13: Group/joint-liability lending -> moderately LOWER predicted default risk (fitted coef. -0.326)
B14: Guarantor Present (1/0) | C14: -0.471 | D14: =EXP(C14) | E14: Guarantor present -> moderately LOWER predicted default risk (fitted coef. -0.471)
B16: Standardisation Parameters (mean, std used to fit the model)
B17: Variable | C17: Mean | D17: Std Dev
B18: Loan Amount (PKR '000) | C18: 153.1544 | D18: 80.2102
B19: Loan Term (months) | C19: 14.52 | D19: 6.691
B20: Borrower Age | C20: 38.94 | D20: 11.9669
B21: Monthly Income (PKR '000) | C21: 72.7312 | D21: 29.4971
B22: Dependents | C22: 2.305 | D22: 1.6947
B23: Previous Loans Completed | C23: 2.44 | D23: 1.6542
B24: Group Lending (1/0) | C24: 0.53 | D24: 0.4991
B25: Guarantor Present (1/0) | C25: 0.605 | D25: 0.4889

Sheet Loan Portfolio & Scoring
A1: Loan ID | B1: Loan Amount (PKR '000) | C1: Loan Term (months) | D1: Borrower Age | E1: Monthly Income (PKR '000) | F1: Dependents | G1: Previous Loans Completed | H1: Group Lending (1/0) | I1: Guarantor Present (1/0) | J1: Z: Loan Amount (PKR '000) | K1: Z: Loan Term (months) | L1: Z: Borrower Age | M1: Z: Monthly Income (PKR '000) | N1: Z: Dependents | O1: Z: Previous Loans Completed | P1: Z: Group Lending (1/0) | Q1: Z: Guarantor Present (1/0) | R1: Log-Odds Score | S1: Predicted Default Probability | T1: Risk Band | U1: Actual Outcome (simulated)
A2: MFI-0001 | B2: 211.06 | C2: 12 | D2: 20 | E2: 53.15 | F2: 3 | G2: 0 | H2: 0 | I2: 1 | J2: =(B2-'Model Coefficients'!$C$18)/'Model Coefficients'!$D$18 | K2: =(C2-'Model Coefficients'!$C$19)/'Model Coefficients'!$D$19 | L2: =(D2-'Model Coefficients'!$C$20)/'Model Coefficients'!$D$20 | M2: =(E2-'Model Coefficients'!$C$21)/'Model Coefficients'!$D$21 | N2: =(F2-'Model Coefficients'!$C$22)/'Model Coefficients'!$D$22 | O2: =(G2-'Model Coefficients'!$C$23)/'Model Coefficients'!$D$23 | P2: =(H2-'Model Coefficients'!$C$24)/'Model Coefficients'!$D$24 | Q2: =(I2-'Model Coefficients'!$C$25)/'Model Coefficients'!$D$25 | R2: ='Model Coefficients'!$C$6+'Model Coefficients'!$C$7*J2+'Model Coefficients'!$C$8*K2+'Model Coefficients'!$C$9*L2+'Model Coefficients'!$C$10*M2+'Model Coefficients'!$C$11*N2+'Model Coefficients'!$C$12*O2+'Model Coefficients'!$C$13*P2+'Model Coefficients'!$C$14*Q2 | S2: =1/(1+EXP(-R2)) | T2: =IF(S2<0.15,"Low Risk",IF(S2<0.35,"Medium Risk","High Risk")) | U2: Repaid
A3: MFI-0002 | B3: 35.07 | C3: 24 | D3: 31 | E3: 39.05 | F3: 0 | G3: 3 | H3: 0 | I3: 1 | J3: =(B3-'Model Coefficients'!$C$18)/'Model Coefficients'!$D$18 | K3: =(C3-'Model Coefficients'!$C$19)/'Model Coefficients'!$D$19 | L3: =(D3-'Model Coefficients'!$C$20)/'Model Coefficients'!$D$20 | M3: =(E3-'Model Coefficients'!$C$21)/'Model Coefficients'!$D$21 | N3: =(F3-'Model Coefficients'!$C$22)/'Model Coefficients'!$D$22 | O3: =(G3-'Model Coefficients'!$C$23)/'Model Coefficients'!$D$23 | P3: =(H3-'Model Coefficients'!$C$24)/'Model Coefficients'!$D$24 | Q3: =(I3-'Model Coefficients'!$C$25)/'Model Coefficients'!$D$25 | R3: ='Model Coefficients'!$C$6+'Model Coefficients'!$C$7*J3+'Model Coefficients'!$C$8*K3+'Model Coefficients'!$C$9*L3+'Model Coefficients'!$C$10*M3+'Model Coefficients'!$C$11*N3+'Model Coefficients'!$C$12*O3+'Model Coefficients'!$C$13*P3+'Model Coefficients'!$C$14*Q3 | S3: =1/(1+EXP(-R3)) | T3: =IF(S3<0.15,"Low Risk",IF(S3<0.35,"Medium Risk","High Risk")) | U3: Repaid
A4: MFI-0003 | B4: 81.7 | C4: 12 | D4: 39 | E4: 56.8 | F4: 4 | G4: 1 | H4: 1 | I4: 1 | J4: =(B4-'Model Coefficients'!$C$18)/'Model Coefficients'!$D$18 | K4: =(C4-'Model Coefficients'!$C$19)/'Model Coefficients'!$D$19 | L4: =(D4-'Model Coefficients'!$C$20)/'Model Coefficients'!$D$20 | M4: =(E4-'Model Coefficients'!$C$21)/'Model Coefficients'!$D$21 | N4: =(F4-'Model Coefficients'!$C$22)/'Model Coefficients'!$D$22 | O4: =(G4-'Model Coefficients'!$C$23)/'Model Coefficients'!$D$23 | P4: =(H4-'Model Coefficients'!$C$24)/'Model Coefficients'!$D$24 | Q4: =(I4-'Model Coefficients'!$C$25)/'Model Coefficients'!$D$25 | R4: ='Model Coefficients'!$C$6+'Model Coefficients'!$C$7*J4+'Model Coefficients'!$C$8*K4+'Model Coefficients'!$C$9*L4+'Model Coefficients'!$C$10*M4+'Model Coefficients'!$C$11*N4+'Model Coefficients'!$C$12*O4+'Model Coefficients'!$C$13*P4+'Model Coefficients'!$C$14*Q4 | S4: =1/(1+EXP(-R4)) | T4: =IF(S4<0.15,"Low Risk",IF(S4<0.35,"Medium Risk","High Risk")) | U4: Repaid
A5: MFI-0004 | B5: 71.62 | C5: 6 | D5: 42 | E5: 75.46 | F5: 5 | G5: 1 | H5: 1 | I5: 1 | J5: =(B5-'Model Coefficients'!$C$18)/'Model Coefficients'!$D$18 | K5: =(C5-'Model Coefficients'!$C$19)/'Model Coefficients'!$D$19 | L5: =(D5-'Model Coefficients'!$C$20)/'Model Coefficients'!$D$20 | M5: =(E5-'Model Coefficients'!$C$21)/'Model Coefficients'!$D$21 | N5: =(F5-'Model Coefficients'!$C$22)/'Model Coefficients'!$D$22 | O5: =(G5-'Model Coefficients'!$C$23)/'Model Coefficients'!$D$23 | P5: =(H5-'Model Coefficients'!$C$24)/'Model Coefficients'!$D$24 | Q5: =(I5-'Model Coefficients'!$C$25)/'Model Coefficients'!$D$25 | R5: ='Model Coefficients'!$C$6+'Model Coefficients'!$C$7*J5+'Model Coefficients'!$C$8*K5+'Model Coefficients'!$C$9*L5+'Model Coefficients'!$C$10*M5+'Model Coefficients'!$C$11*N5+'Model Coefficients'!$C$12*O5+'Model Coefficients'!$C$13*P5+'Model Coefficients'!$C$14*Q5 | S5: =1/(1+EXP(-R5)) | T5: =IF(S5<0.15,"Low Risk",IF(S5<0.35,"Medium Risk","High Risk")) | U5: Repaid
A6: MFI-0005 | B6: 69.25 | C6: 6 | D6: 50 | E6: 95.53 | F6: 2 | G6: 0 | H6: 0 | I6: 0 | J6: =(B6-'Model Coefficients'!$C$18)/'Model Coefficients'!$D$18 | K6: =(C6-'Model Coefficients'!$C$19)/'Model Coefficients'!$D$19 | L6: =(D6-'Model Coefficients'!$C$20)/'Model Coefficients'!$D$20 | M6: =(E6-'Model Coefficients'!$C$21)/'Model Coefficients'!$D$21 | N6: =(F6-'Model Coefficients'!$C$22)/'Model Coefficients'!$D$22 | O6: =(G6-'Model Coefficients'!$C$23)/'Model Coefficients'!$D$23 | P6: =(H6-'Model Coefficients'!$C$24)/'Model Coefficients'!$D$24 | Q6: =(I6-'Model Coefficients'!$C$25)/'Model Coefficients'!$D$25 | R6: ='Model Coefficients'!$C$6+'Model Coefficients'!$C$7*J6+'Model Coefficients'!$C$8*K6+'Model Coefficients'!$C$9*L6+'Model Coefficients'!$C$10*M6+'Model Coefficients'!$C$11*N6+'Model Coefficients'!$C$12*O6+'Model Coefficients'!$C$13*P6+'Model Coefficients'!$C$14*Q6 | S6: =1/(1+EXP(-R6)) | T6: =IF(S6<0.15,"Low Risk",IF(S6<0.35,"Medium Risk","High Risk")) | U6: Repaid
A7: MFI-0006 | B7: 247.39 | C7: 12 | D7: 41 | E7: 115.75 | F7: 5 | G7: 2 | H7: 1 | I7: 1 | J7: =(B7-'Model Coefficients'!$C$18)/'Model Coefficients'!$D$18 | K7: =(C7-'Model Coefficients'!$C$19)/'Model Coefficients'!$D$19 | L7: =(D7-'Model Coefficients'!$C$20)/'Model Coefficients'!$D$20 | M7: =(E7-'Model Coefficients'!$C$21)/'Model Coefficients'!$D$21 | N7: =(F7-'Model Coefficients'!$C$22)/'Model Coefficients'!$D$22 | O7: =(G7-'Model Coefficients'!$C$23)/'Model Coefficients'!$D$23 | P7: =(H7-'Model Coefficients'!$C$24)/'Model Coefficients'!$D$24 | Q7: =(I7-'Model Coefficients'!$C$25)/'Model Coefficients'!$D$25 | R7: ='Model Coefficients'!$C$6+'Model Coefficients'!$C$7*J7+'Model Coefficients'!$C$8*K7+'Model Coefficients'!$C$9*L7+'Model Coefficients'!$C$10*M7+'Model Coefficients'!$C$11*N7+'Model Coefficients'!$C$12*O7+'Model Coefficients'!$C$13*P7+'Model Coefficients'!$C$14*Q7 | S7: =1/(1+EXP(-R7)) | T7: =IF(S7<0.15,"Low Risk",IF(S7<0.35,"Medium Risk","High Risk")) | U7: Repaid
A8: MFI-0007 | B8: 278.54 | C8: 24 | D8: 21 | E8: 106.71 | F8: 1 | G8: 5 | H8: 1 | I8: 0 | J8: =(B8-'Model Coefficients'!$C$18)/'Model Coefficients'!$D$18 | K8: =(C8-'Model Coefficients'!$C$19)/'Model Coefficients'!$D$19 | L8: =(D8-'Model Coefficients'!$C$20)/'Model Coefficients'!$D$20 | M8: =(E8-'Model Coefficients'!$C$21)/'Model Coefficients'!$D$21 | N8: =(F8-'Model Coefficients'!$C$22)/'Model Coefficients'!$D$22 | O8: =(G8-'Model Coefficients'!$C$23)/'Model Coefficients'!$D$23 | P8: =(H8-'Model Coefficients'!$C$24)/'Model Coefficients'!$D$24 | Q8: =(I8-'Model Coefficients'!$C$25)/'Model Coefficients'!$D$25 | R8: ='Model Coefficients'!$C$6+'Model Coefficients'!$C$7*J8+'Model Coefficients'!$C$8*K8+'Model Coefficients'!$C$9*L8+'Model Coefficients'!$C$10*M8+'Model Coefficients'!$C$11*N8+'Model Coefficients'!$C$12*O8+'Model Coefficients'!$C$13*P8+'Model Coefficients'!$C$14*Q8 | S8: =1/(1+EXP(-R8)) | T8: =IF(S8<0.15,"Low Risk",IF(S8<0.35,"Medium Risk","High Risk")) | U8: Repaid
A9: MFI-0008 | B9: 97.44 | C9: 12 | D9: 37 | E9: 97.72 | F9: 1 | G9: 3 | H9: 1 | I9: 0 | J9: =(B9-'Model Coefficients'!$C$18)/'Model Coefficients'!$D$18 | K9: =(C9-'Model Coefficients'!$C$19)/'Model Coefficients'!$D$19 | L9: =(D9-'Model Coefficients'!$C$20)/'Model Coefficients'!$D$20 | M9: =(E9-'Model Coefficients'!$C$21)/'Model Coefficients'!$D$21 | N9: =(F9-'Model Coefficients'!$C$22)/'Model Coefficients'!$D$22 | O9: =(G9-'Model Coefficients'!$C$23)/'Model Coefficients'!$D$23 | P9: =(H9-'Model Coefficients'!$C$24)/'Model Coefficients'!$D$24 | Q9: =(I9-'Model Coefficients'!$C$25)/'Model Coefficients'!$D$25 | R9: ='Model Coefficients'!$C$6+'Model Coefficients'!$C$7*J9+'Model Coefficients'!$C$8*K9+'Model Coefficients'!$C$9*L9+'Model Coefficients'!$C$10*M9+'Model Coefficients'!$C$11*N9+'Model Coefficients'!$C$12*O9+'Model Coefficients'!$C$13*P9+'Model Coefficients'!$C$14*Q9 | S9: =1/(1+EXP(-R9)) | T9: =IF(S9<0.15,"Low Risk",IF(S9<0.35,"Medium Risk","High Risk")) | U9: Repaid
A10: MFI-0009 | B10: 249.53 | C10: 12 | D10: 37 | E10: 109.57 | F10: 4 | G10: 0 | H10: 1 | I10: 1 | J10: =(B10-'Model Coefficients'!$C$18)/'Model Coefficients'!$D$18 | K10: =(C10-'Model Coefficients'!$C$19)/'Model Coefficients'!$D$19 | L10: =(D10-'Model Coefficients'!$C$20)/'Model Coefficients'!$D$20 | M10: =(E10-'Model Coefficients'!$C$21)/'Model Coefficients'!$D$21 | N10: =(F10-'Model Coefficients'!$C$22)/'Model Coefficients'!$D$22 | O10: =(G10-'Model Coefficients'!$C$23)/'Model Coefficients'!$D$23 | P10: =(H10-'Model Coefficients'!$C$24)/'Model Coefficients'!$D$24 | Q10: =(I10-'Model Coefficients'!$C$25)/'Model Coefficients'!$D$25 | R10: ='Model Coefficients'!$C$6+'Model Coefficients'!$C$7*J10+'Model Coefficients'!$C$8*K10+'Model Coefficients'!$C$9*L10+'Model Coefficients'!$C$10*M10+'Model Coefficients'!$C$11*N10+'Model Coefficients'!$C$12*O10+'Model Coefficients'!$C$13*P10+'Model Coefficients'!$C$14*Q10 | S10: =1/(1+EXP(-R10)) | T10: =IF(S10<0.15,"Low Risk",IF(S10<0.35,"Medium Risk","High Risk")) | U10: Defaulted
A11: MFI-0010 | B11: 269.17 | C11: 12 | D11: 34 | E11: 88.09 | F11: 4 | G11: 1 | H11: 1 | I11: 0 | J11: =(B11-'Model Coefficients'!$C$18)/'Model Coefficients'!$D$18 | K11: =(C11-'Model Coefficients'!$C$19)/'Model Coefficients'!$D$19 | L11: =(D11-'Model Coefficients'!$C$20)/'Model Coefficients'!$D$20 | M11: =(E11-'Model Coefficients'!$C$21)/'Model Coefficients'!$D$21 | N11: =(F11-'Model Coefficients'!$C$22)/'Model Coefficients'!$D$22 | O11: =(G11-'Model Coefficients'!$C$23)/'Model Coefficients'!$D$23 | P11: =(H11-'Model Coefficients'!$C$24)/'Model Coefficients'!$D$24 | Q11: =(I11-'Model Coefficients'!$C$25)/'Model Coefficients'!$D$25 | R11: ='Model Coefficients'!$C$6+'Model Coefficients'!$C$7*J11+'Model Coefficients'!$C$8*K11+'Model Coefficients'!$C$9*L11+'Model Coefficients'!$C$10*M11+'Model Coefficients'!$C$11*N11+'Model Coefficients'!$C$12*O11+'Model Coefficients'!$C$13*P11+'Model Coefficients'!$C$14*Q11 | S11: =1/(1+EXP(-R11)) | T11: =IF(S11<0.15,"Low Risk",IF(S11<0.35,"Medium Risk","High Risk")) | U11: Defaulted
A12: MFI-0011 | B12: 163.63 | C12: 6 | D12: 31 | E12: 114.28 | F12: 0 | G12: 1 | H12: 1 | I12: 1 | J12: =(B12-'Model Coefficients'!$C$18)/'Model Coefficients'!$D$18 | K12: =(C12-'Model Coefficients'!$C$19)/'Model Coefficients'!$D$19 | L12: =(D12-'Model Coefficients'!$C$20)/'Model Coefficients'!$D$20 | M12: =(E12-'Model Coefficients'!$C$21)/'Model Coefficients'!$D$21 | N12: =(F12-'Model Coefficients'!$C$22)/'Model Coefficients'!$D$22 | O12: =(G12-'Model Coefficients'!$C$23)/'Model Coefficients'!$D$23 | P12: =(H12-'Model Coefficients'!$C$24)/'Model Coefficients'!$D$24 | Q12: =(I12-'Model Coefficients'!$C$25)/'Model Coefficients'!$D$25 | R12: ='Model Coefficients'!$C$6+'Model Coefficients'!$C$7*J12+'Model Coefficients'!$C$8*K12+'Model Coefficients'!$C$9*L12+'Model Coefficients'!$C$10*M12+'Model Coefficients'!$C$11*N12+'Model Coefficients'!$C$12*O12+'Model Coefficients'!$C$13*P12+'Model Coefficients'!$C$14*Q12 | S12: =1/(1+EXP(-R12)) | T12: =IF(S12<0.15,"Low Risk",IF(S12<0.35,"Medium Risk","High Risk")) | U12: Repaid
A13: MFI-0012 | B13: 88.59 | C13: 6 | D13: 41 | E13: 68.92 | F13: 0 | G13: 1 | H13: 1 | I13: 1 | J13: =(B13-'Model Coefficients'!$C$18)/'Model Coefficients'!$D$18 | K13: =(C13-'Model Coefficients'!$C$19)/'Model Coefficients'!$D$19 | L13: =(D13-'Model Coefficients'!$C$20)/'Model Coefficients'!$D$20 | M13: =(E13-'Model Coefficients'!$C$21)/'Model Coefficients'!$D$21 | N13: =(F13-'Model Coefficients'!$C$22)/'Model Coefficients'!$D$22 | O13: =(G13-'Model Coefficients'!$C$23)/'Model Coefficients'!$D$23 | P13: =(H13-'Model Coefficients'!$C$24)/'Model Coefficients'!$D$24 | Q13: =(I13-'Model Coefficients'!$C$25)/'Model Coefficients'!$D$25 | R13: ='Model Coefficients'!$C$6+'Model Coefficients'!$C$7*J13+'Model Coefficients'!$C$8*K13+'Model Coefficients'!$C$9*L13+'Model Coefficients'!$C$10*M13+'Model Coefficients'!$C$11*N13+'Model Coefficients'!$C$12*O13+'Model Coefficients'!$C$13*P13+'Model Coefficients'!$C$14*Q13 | S13: =1/(1+EXP(-R13)) | T13: =IF(S13<0.15,"Low Risk",IF(S13<0.35,"Medium Risk","High Risk")) | U13: Repaid
... A201: MFI-0200 | B201: 95.42 | C201: 12 | D201: 46 | E201: 37.55 | F201: 4 | G201: 1 | H201: 0 | I201: 1 | J201: =(B201-'Model Coefficients'!$C$18)/'Model Coefficients'!$D$18 | K201: =(C201-'Model Coefficients'!$C$19)/'Model Coefficients'!$D$19 | L201: =(D201-'Model Coefficients'!$C$20)/'Model Coefficients'!$D$20 | M201: =(E201-'Model Coefficients'!$C$21)/'Model Coefficients'!$D$21 | N201: =(F201-'Model Coefficients'!$C$22)/'Model Coefficients'!$D$22 | O201: =(G201-'Model Coefficients'!$C$23)/'Model Coefficients'!$D$23 | P201: =(H201-'Model Coefficients'!$C$24)/'Model Coefficients'!$D$24 | Q201: =(I201-'Model Coefficients'!$C$25)/'Model Coefficients'!$D$25 | R201: ='Model Coefficients'!$C$6+'Model Coefficients'!$C$7*J201+'Model Coefficients'!$C$8*K201+'Model Coefficients'!$C$9*L201+'Model Coefficients'!$C$10*M201+'Model Coefficients'!$C$11*N201+'Model Coefficients'!$C$12*O201+'Model Coefficients'!$C$13*P201+'Model Coefficients'!$C$14*Q201 | S201: =1/(1+EXP(-R201)) | T201: =IF(S201<0.15,"Low Risk",IF(S201<0.35,"Medium Risk","High Risk")) | U201: Repaid

Sheet Model Validation
B2: Model Validation - Decile (Gains) Table, Confusion Matrix, KS Statistic
B3: Loans are ranked by predicted default probability and split into 10 equal deciles (decile 10 = highest risk).
B5: Decile (1=Lowest Risk,10=Highest Risk) | C5: # Loans | D5: Avg Predicted Prob. | E5: Actual Default Rate
B6: 1 | C6: 20 | D6: 0.0098 | E6: 0
B7: 2 | C7: 20 | D7: 0.0223 | E7: 0.05
B8: 3 | C8: 20 | D8: 0.0417 | E8: 0.1
B9: 4 | C9: 20 | D9: 0.0782 | E9: 0.1
B10: 5 | C10: 20 | D10: 0.1135 | E10: 0.05
B11: 6 | C11: 20 | D11: 0.1767 | E11: 0.05
B12: 7 | C12: 20 | D12: 0.2621 | E12: 0.15
B13: 8 | C13: 20 | D13: 0.3837 | E13: 0.55
B14: 9 | C14: 20 | D14: 0.5601 | E14: 0.5
B15: 10 | C15: 20 | D15: 0.8018 | E15: 0.9
B17: KS Statistic (max separation between cumulative %bad and %good) | D17: 0.6568
B18: Interpretation: KS > 20% is considered acceptable discrimination for a credit-risk scorecard; > 40% is strong.
B20: Confusion Matrix at Probability Cutoff = 30%
C21: Predicted: Repaid | D21: Predicted: Default
B22: Actual: Repaid | C22: 128 | D22: 23
B23: Actual: Default | C23: 8 | D23: 41
B25: Accuracy | D25: 0.845
B26: Precision (of predicted defaults, % that actually defaulted) | D26: 0.6406
B27: Recall (of actual defaults, % correctly flagged) | D27: 0.8367

Sheet Dashboard
B2: Model Validation Dashboard

Sheet Insights
B2: Key Findings & Recommendations
B4: 1. THE MODEL RANK-ORDERS RISK WELL: actual default rate rises close to monotonically from decile 1 (lowest
B5: predicted risk) to decile 10 (highest predicted risk) - the core requirement of any usable credit-risk model,
B6: confirmed here with a KS statistic of 65.7%, comfortably above the ~20% threshold generally considered
B7: acceptable discrimination for a scorecard.
B8: 2. MONTHLY INCOME AND LOAN AMOUNT ARE THE TWO STRONGEST DRIVERS of predicted default risk (largest standardised
B9: coefficients, both larger than dependents, age, prior-loan track record, or group-lending status) - and they
B10: point in opposite, mutually reinforcing directions (higher income lowers risk, a larger loan raises it),
B11: consistent with the well-established microfinance finding that affordability relative to income matters more
B12: than almost any other single factor.
B13: 3. GROUP/JOINT-LIABILITY LENDING AND GUARANTORS BOTH REDUCE PREDICTED DEFAULT RISK - a direct, quantified
B14: confirmation of the core insight behind the Grameen-style group-lending model that much of microfinance is
... B25: confusion matrix - the two projects together show both ends of a real credit-risk model's lifecycle.
